<?xml version="1.0" encoding="utf-8" ?><dwsync><file name="basic.css" server="ftp.kamakuralive.net//ssl/" local="3588552111" remote="3566991600" Dst="-1" /><file name="DSC02516.jpg" server="ftp.kamakuralive.net//ssl/" local="3588552111" remote="3566991600" Dst="-1" /><file name="DSC02517.jpg" server="ftp.kamakuralive.net//ssl/" local="3588552111" remote="3566991600" Dst="-1" /><file name="DSC02577.jpg" server="ftp.kamakuralive.net//ssl/" local="3588552111" remote="3566991600" Dst="-1" /><file name="DSC02720.jpg" server="ftp.kamakuralive.net//ssl/" local="3588552111" remote="3566991600" Dst="-1" /><file name="DSC02732.jpg" server="ftp.kamakuralive.net//ssl/" local="3588552111" remote="3566991600" Dst="-1" /><file name="DSC02750.jpg" server="ftp.kamakuralive.net//ssl/" local="3588552111" remote="3566991600" Dst="-1" /><file name="DSC02736.jpg" server="ftp.kamakuralive.net//ssl/" local="3588552112" remote="3566991600" Dst="-1" /><file name="DSC02809.jpg" server="ftp.kamakuralive.net//ssl/" local="3588552112" remote="3566991600" Dst="-1" /><file name="DSC04682.jpg" server="ftp.kamakuralive.net//ssl/" local="3588552112" remote="3566991600" Dst="-1" /><file name="DSC04691.jpg" server="ftp.kamakuralive.net//ssl/" local="3588552112" remote="3566991600" Dst="-1" /><file name="DSC04747.jpg" server="ftp.kamakuralive.net//ssl/" local="3588552112" remote="3566991600" Dst="-1" /><file name="DSC04786.jpg" server="ftp.kamakuralive.net//ssl/" local="3588552112" remote="3566991600" Dst="-1" /><file name="DSC07353.jpg" server="ftp.kamakuralive.net//ssl/" local="3588552112" remote="3566991600" Dst="-1" /><file name="DSC07358.jpg" server="ftp.kamakuralive.net//ssl/" local="3588552112" remote="3566991600" Dst="-1" /></dwsync>